{"dates":[{"date":"Jun 19, 2019","hasGoal":false,"hasRevenue":false,"sessionCount":2,"sessions":[{"duration":"00:00","deviceCategory":"mobile","channel":"Direct","activitySummary":{"PAGEVIEW":"1"},"activities":[{"time":"7:27 PM","type":"PAGEVIEW","repeatActivityTimes":[],"details":[{"Page title":["SMART BUY SOLUTIONS"],"Page URL":["/"]}],"pageTitle":"SMART BUY SOLUTIONS"}]},{"duration":"01:29","deviceCategory":"mobile","channel":"Direct","activitySummary":{"PAGEVIEW":"2"},"activities":[{"time":"6:16 PM","type":"PAGEVIEW","repeatActivityTimes":[],"details":[{"Page title":["SMART BUY SOLUTIONS"],"Page URL":["/"]}],"pageTitle":"SMART BUY SOLUTIONS"},{"time":"6:15 PM","type":"PAGEVIEW","repeatActivityTimes":[],"details":[{"Page title":["SMART BUY SOLUTIONS"],"Page URL":["/"]}],"pageTitle":"SMART BUY SOLUTIONS"}]}]}]}